src/__init__.py
src/config.py
src/image_process.py
src/image_reco.py
src/test.py
src/text_process.py
src/video_process.py
videoTotext-1.0.dist-info/METADATA
videoTotext-1.0.dist-info/WHEEL
videoTotext-1.0.dist-info/top_level.txt
videoTotext-1.0.dist-info/RECORD
