Metadata-Version: 2.1
Name: videoTotext
Version: 1.0
Summary: 동영상에서 세부 글자(자막, 타이틀) 추출
Home-page: https://github.com/jihaeK/videoTotext
Author: JiHae Kim
Author-email: jihae6020@gmail.com
License: UNKNOWN
Download-URL: https://githur.com/jihaeK/videoTotext/archive/1.0.tar.gz
Keywords: liquibase,db migration
Platform: UNKNOWN
Classifier: Programming Language :: Python :: 3
Classifier: License :: OSI Approved :: MIT License
Classifier: Operating System :: OS Independent
Requires-Python: >=3
